lammps_doc/__init__.py
lammps_doc-0.0.3.dist-info/METADATA
lammps_doc-0.0.3.dist-info/WHEEL
lammps_doc-0.0.3.dist-info/top_level.txt
lammps_doc-0.0.3.dist-info/RECORD
