Metadata-Version: 2.1
Name: lammps-doc
Version: 0.0.3
Author: Harish PVV
Author-email: harishpvv@gmail.com
License: MIT
Keywords: lammps documentation
Classifier: Programming Language :: Python :: 3
Classifier: License :: OSI Approved :: MIT License
Classifier: Operating System :: OS Independent
Requires-Dist: beautifulsoup4
